simpsom/__init__.py
simpsom/_version.py
simpsom/hexagons.py
simpsom/interface.py
simpsom/network.py
simpsom/cluster/__init__.py
simpsom/cluster/density_peak.py
simpsom/cluster/quality_threshold.py
simpsom-2.0.2.dist-info/LICENSE.txt
simpsom-2.0.2.dist-info/METADATA
simpsom-2.0.2.dist-info/WHEEL
simpsom-2.0.2.dist-info/top_level.txt
simpsom-2.0.2.dist-info/RECORD
