Metadata-Version: 2.1
Name: simpsom
Version: 2.0.2
Summary: Simple Self-Organizing Maps in Python
Home-page: https://github.com/fcomitani/simpsom
Download-URL: https://github.com/fcomitani/simpsom/archive/2.0.2.tar.gz
Author: Federico Comitani
Author-email: federico.comitani@gmail.com
License: MIT
Keywords: kohonen self-organizing maps,self-organizing maps,clustering,dimension-reduction,som
Classifier: Development Status :: 4 - Beta
Classifier: Intended Audience :: Science/Research
Classifier: Topic :: Scientific/Engineering
Classifier: License :: OSI Approved :: MIT License
Classifier: Programming Language :: Python
Classifier: Programming Language :: Python :: 3
License-File: LICENSE.txt
Requires-Dist: numpy (>=1.19.5)
Requires-Dist: scikit-learn (>=0.22.2.post1)
Requires-Dist: matplotlib (>=3.3.3)
Provides-Extra: gpu
Requires-Dist: cupy (==8.60) ; extra == 'gpu'
Requires-Dist: cuml (==0.18) ; extra == 'gpu'
